evalai/__init__.py
evalai/api.py
evalai/config.py
evalaii-0.3.0.dist-info/LICENSE
evalaii-0.3.0.dist-info/METADATA
evalaii-0.3.0.dist-info/WHEEL
evalaii-0.3.0.dist-info/top_level.txt
evalaii-0.3.0.dist-info/RECORD
