Metadata-Version: 2.1
Name: evalaii
Version: 0.3.0
Summary: A helper library for handling LLM evaluation systems
Home-page: https://github.com/poemsforaphrodite/eval
Author: Pushpender Solanki
Author-email: pushpendersolanki895@gmail.com
Classifier: Programming Language :: Python :: 3
Classifier: License :: OSI Approved :: MIT License
Classifier: Operating System :: OS Independent
License-File: LICENSE
Requires-Dist: pymongo
Requires-Dist: bcrypt
Requires-Dist: openai
Requires-Dist: pinecone-client
Requires-Dist: aiohttp
